nonebot_plugin_repeat_checker/__init__.py
nonebot_plugin_repeat_checker/checker.py
nonebot_plugin_repeat_checker/config.py
nonebot_plugin_repeat_checker/database.py
nonebot_plugin_repeat_checker/utils.py
nonebot_plugin_repeat_checker-1.2.5.dist-info/licenses/LICENSE
nonebot_plugin_repeat_checker-1.2.5.dist-info/METADATA
nonebot_plugin_repeat_checker-1.2.5.dist-info/WHEEL
nonebot_plugin_repeat_checker-1.2.5.dist-info/top_level.txt
nonebot_plugin_repeat_checker-1.2.5.dist-info/RECORD
