Metadata-Version: 2.4
Name: nonebot-plugin-repeat-checker
Version: 1.2.5
Summary: A NoneBot2 plugin to detect and ban repeat messages in groups
Author-email: SuperWaterGod <yancaiwudi@foxmail.com>
License: AGPL-3.0
Project-URL: Homepage, https://github.com/SuperWaterGod/nonebot-plugin-repeat-checker
Project-URL: Repository, https://github.com/SuperWaterGod/nonebot-plugin-repeat-checker.git
Project-URL: Documentation, https://github.com/SuperWaterGod/nonebot-plugin-repeat-checker#readme
Keywords: nonebot,nonebot2,plugin,repeat,ban,group
Classifier: Development Status :: 4 - Beta
Classifier: Framework :: AsyncIO
Classifier: License :: OSI Approved :: GNU Affero General Public License v3
Classifier: Operating System :: OS Independent
Classifier: Programming Language :: Python :: 3
Classifier: Programming Language :: Python :: 3.8
Classifier: Programming Language :: Python :: 3.9
Classifier: Programming Language :: Python :: 3.10
Classifier: Programming Language :: Python :: 3.11
Requires-Python: >=3.8
License-File: LICENSE
Requires-Dist: nonebot2>=2.4.2
Requires-Dist: nonebot-adapter-onebot>=2.3.0
Requires-Dist: nonebot-plugin-localstore>=0.7.4
Requires-Dist: aiosqlite>=0.17.0
Requires-Dist: unidecode>=1.3.0
Dynamic: license-file
